package/__init__.py
package/manage.py
package/DashAm/__init__.py
package/DashAm/asgi.py
package/DashAm/settings.py
package/DashAm/urls.py
package/DashAm/wsgi.py
package/backend/__init__.py
package/backend/admin.py
package/backend/apps.py
package/backend/forms.py
package/backend/models.py
package/backend/tests.py
package/backend/text.py
package/backend/views.py
package/backend/css/__init__.py
package/backend/css/catalog.py
package/backend/css/menu.py
package/backend/css/slider_css.py
package/backend/functions/__init__.py
package/backend/functions/email_sender.py
package/backend/migrations/0001_initial.py
package/backend/migrations/0002_media_image_news_image.py
package/backend/migrations/0003_category_text.py
package/backend/migrations/0004_remove_category_text.py
package/backend/migrations/0005_category_text.py
package/backend/migrations/0006_alter_media_image.py
package/backend/migrations/0007_alter_media_image_alter_news_image.py
package/backend/migrations/0008_alter_media_image.py
package/backend/migrations/0009_order_description.py
package/backend/migrations/0010_orderphoto_order_photos.py
package/backend/migrations/0011_remove_order_photos_delete_orderphoto.py
package/backend/migrations/0012_alter_news_date.py
package/backend/migrations/0013_alter_category_options_alter_media_options_and_more.py
package/backend/migrations/0014_remove_like_user_id_like_ip_address.py
package/backend/migrations/0015_alter_like_unique_together.py
package/backend/migrations/0016_ipmodel_media_likes.py
package/backend/migrations/0017_remove_media_likes_media_views_delete_like.py
package/backend/migrations/0018_alter_media_views.py
package/backend/migrations/__init__.py
package/backend/templates/NEW.py
package/backend/templates/__init__.py
package/backend/templates/base.py
package/backend/templates/detailed_news.py
package/backend/templates/login.py
package/backend/templates/menu.py
package/backend/templates/menuvar.py
package/backend/templates/news.py
django_afg_simpleforms-1.1.3.dist-info/LICENSE
django_afg_simpleforms-1.1.3.dist-info/METADATA
django_afg_simpleforms-1.1.3.dist-info/WHEEL
django_afg_simpleforms-1.1.3.dist-info/top_level.txt
django_afg_simpleforms-1.1.3.dist-info/RECORD
